winotify.py
winotify/__init__.py
winotify/__main__.py
winotify/_communication.py
winotify/_notify.py
winotify/_registry.py
winotify/audio.py
winotify/communication.py
winotify-1.1.0.dist-info/LICENSE
winotify-1.1.0.dist-info/METADATA
winotify-1.1.0.dist-info/WHEEL
winotify-1.1.0.dist-info/entry_points.txt
winotify-1.1.0.dist-info/top_level.txt
winotify-1.1.0.dist-info/RECORD
