Metadata-Version: 2.1
Name: winotify
Version: 1.1.0
Summary: Show notification toast on Windows 10
Home-page: https://github.com/versa-syahptr/winotify
Author: versa
Author-email: versa1220@gmail.com
License: MIT
Platform: UNKNOWN
Classifier: License :: OSI Approved :: MIT License
Classifier: Programming Language :: Python :: 3
Classifier: Programming Language :: Python :: 3.7
License-File: LICENSE
